lmquery/__init__.py
lmquery/engine.py
lmquery-0.1.0.dist-info/licenses/LICENSE
lmquery-0.1.0.dist-info/METADATA
lmquery-0.1.0.dist-info/WHEEL
lmquery-0.1.0.dist-info/top_level.txt
lmquery-0.1.0.dist-info/RECORD
